MANIFEST.in
README.markdown
setup.py
django_password.egg-info/PKG-INFO
django_password.egg-info/SOURCES.txt
django_password.egg-info/dependency_links.txt
django_password.egg-info/not-zip-safe
django_password.egg-info/requires.txt
django_password.egg-info/top_level.txt
password/__init__.py
password/admin.py
password/forms.py
password/models.py
password/tests.py
password/migrations/0001_initial.py
password/migrations/0002_add_group.py
password/migrations/0003_upgrade_encryption_to_aes.py
password/migrations/0004_upgrade_encryption_to_aes.py
password/migrations/__init__.py