Metadata-Version: 1.0
Name: django-password
Version: 3.0
Summary: A Django application to store communal passwords.
Home-page: http://github.com/ghickman/django-password
Author: George Hickman
Author-email: george@ghickman.co.uk
License: MIT
Keywords: django password
Platform: UNKNOWN
Classifier: Framework :: Django
Classifier: Development Status :: 4 - Beta
Classifier: Programming Language :: Python
Classifier: Environment :: Web Environment
Classifier: Operating System :: OS Independent
Classifier: Intended Audience :: Developers
Classifier: Intended Audience :: System Administrators
Classifier: License :: OSI Approved :: MIT License
Classifier: Topic :: System :: Software Distribution
Classifier: Programming Language :: Python
Classifier: Topic :: Software Development :: Libraries :: Python Modules
